Metadata-Version: 2.1
Name: tartiflette-scalars
Version: 0.0.5
Summary: tartiflette_scalars
Home-page: https://github.com/remorses/tartiflette_scalars
Author: Tommaso De Rossi
Author-email: daer.tommy@gmail.com
License: Apache Software License 2.0
Keywords: TODO
Platform: UNKNOWN
Classifier: Intended Audience :: Information Technology
Classifier: Programming Language :: Python :: 3
Classifier: Programming Language :: Python :: 3.6
Classifier: Programming Language :: Python :: 3.7
